ras_commander/BcoMonitor.py
ras_commander/Decorators.py
ras_commander/ExecutionCallback.py
ras_commander/LoggingConfig.py
ras_commander/M3Model.py
ras_commander/RasBco.py
ras_commander/RasBreach.py
ras_commander/RasCmdr.py
ras_commander/RasControl.py
ras_commander/RasCurrency.py
ras_commander/RasExamples.py
ras_commander/RasGeo.py
ras_commander/RasGeometry.py
ras_commander/RasGeometryUtils.py
ras_commander/RasGuiAutomation.py
ras_commander/RasMap.py
ras_commander/RasPlan.py
ras_commander/RasPrj.py
ras_commander/RasProcess.py
ras_commander/RasScreenshot.py
ras_commander/RasUnsteady.py
ras_commander/RasUtils.py
ras_commander/RasValidation.py
ras_commander/__init__.py
ras_commander/callbacks.py
ras_commander/ebfe_examples.py
ras_commander/ebfe_models.py
ras_commander/validation_base.py
ras_commander/check/RasCheck.py
ras_commander/check/__init__.py
ras_commander/check/messages.py
ras_commander/check/report.py
ras_commander/check/thresholds.py
ras_commander/dss/RasDss.py
ras_commander/dss/__init__.py
ras_commander/dss/_hec_monolith.py
ras_commander/fixit/RasFixit.py
ras_commander/fixit/__init__.py
ras_commander/fixit/log_parser.py
ras_commander/fixit/obstructions.py
ras_commander/fixit/results.py
ras_commander/fixit/visualization.py
ras_commander/geom/GeomBridge.py
ras_commander/geom/GeomCrossSection.py
ras_commander/geom/GeomCulvert.py
ras_commander/geom/GeomHtab.py
ras_commander/geom/GeomHtabUtils.py
ras_commander/geom/GeomInlineWeir.py
ras_commander/geom/GeomLandCover.py
ras_commander/geom/GeomLateral.py
ras_commander/geom/GeomMetadata.py
ras_commander/geom/GeomParser.py
ras_commander/geom/GeomPreprocessor.py
ras_commander/geom/GeomStorage.py
ras_commander/geom/__init__.py
ras_commander/hdf/HdfBase.py
ras_commander/hdf/HdfBenefitAreas.py
ras_commander/hdf/HdfBndry.py
ras_commander/hdf/HdfFluvialPluvial.py
ras_commander/hdf/HdfHydraulicTables.py
ras_commander/hdf/HdfInfiltration.py
ras_commander/hdf/HdfMesh.py
ras_commander/hdf/HdfPipe.py
ras_commander/hdf/HdfPlan.py
ras_commander-0.88.6.dist-info/licenses/LICENSE
ras_commander-0.88.6.dist-info/METADATA
ras_commander-0.88.6.dist-info/WHEEL
ras_commander-0.88.6.dist-info/top_level.txt
ras_commander-0.88.6.dist-info/RECORD
