Metadata-Version: 2.4
Name: ras-commander
Version: 0.88.6
Summary: A Python library for automating HEC-RAS 6.x operations
Home-page: https://github.com/gpt-cmdr/ras-commander
Author: William M. Katzenmeyer, P.E., C.F.M.
Author-email: heccommander@gmail.com
Requires-Python: >=3.10
License-File: LICENSE
Requires-Dist: h5py
Requires-Dist: numpy
Requires-Dist: pandas
Requires-Dist: requests
Requires-Dist: tqdm
Requires-Dist: scipy
Requires-Dist: xarray
Requires-Dist: geopandas
Requires-Dist: matplotlib
Requires-Dist: shapely
Requires-Dist: rasterstats
Requires-Dist: rtree
Requires-Dist: fsspec>=2023.0.0
Requires-Dist: pywin32>=227; sys_platform == "win32"
Requires-Dist: psutil>=5.6.6
Requires-Dist: hms-commander>=0.2.0
Provides-Extra: remote
Provides-Extra: remote-ssh
Requires-Dist: paramiko>=3.0; extra == "remote-ssh"
Provides-Extra: remote-winrm
Requires-Dist: pywinrm>=0.4.3; extra == "remote-winrm"
Provides-Extra: remote-docker
Requires-Dist: docker>=6.0; extra == "remote-docker"
Provides-Extra: remote-aws
Requires-Dist: boto3>=1.28; extra == "remote-aws"
Provides-Extra: remote-azure
Requires-Dist: azure-identity>=1.14; extra == "remote-azure"
Requires-Dist: azure-mgmt-compute>=30.0; extra == "remote-azure"
Provides-Extra: remote-all
Requires-Dist: paramiko>=3.0; extra == "remote-all"
Requires-Dist: pywinrm>=0.4.3; extra == "remote-all"
Requires-Dist: docker>=6.0; extra == "remote-all"
Requires-Dist: boto3>=1.28; extra == "remote-all"
Requires-Dist: azure-identity>=1.14; extra == "remote-all"
Requires-Dist: azure-mgmt-compute>=30.0; extra == "remote-all"
Provides-Extra: gui
Requires-Dist: Pillow>=9.0; extra == "gui"
Provides-Extra: precip-huc12
Requires-Dist: pygeohydro>=0.19.0; extra == "precip-huc12"
Dynamic: author
Dynamic: author-email
Dynamic: description
Dynamic: description-content-type
Dynamic: home-page
Dynamic: license-file
Dynamic: provides-extra
Dynamic: requires-dist
Dynamic: requires-python
Dynamic: summary
